{
	"events": [
		{
			"character": "",
			"event_id": "dialogic_001",
			"portrait": "",
			"text": "Gare Lille Flandres, jeudi 4 mai 2023"
		},
		{
			"audio_bus": "Ambient",
			"background-music": "play",
			"event_id": "dialogic_031",
			"event_name": "BackgroundMusic",
			"fade_length": 1,
			"file": "res://audios/effects/crowd.mp3",
			"volume": 0
		},
		{
			"character": "character-1677363460.json",
			"event_id": "dialogic_001",
			"portrait": "",
			"text": "Raahh, c'est pas possible!"
		},
		{
			"character": "character-1677363460.json",
			"event_id": "dialogic_001",
			"portrait": "",
			"text": "Y a un monde de fou, je vais être en retard!"
		},
		{
			"event_id": "dialogic_023",
			"hide_dialogbox": true,
			"wait_seconds": 2
		},
		{
			"character": "character-1677363460.json",
			"event_id": "dialogic_001",
			"portrait": "",
			"text": "Je vais rentrer dans ce métro, il y a l'air d'avoir un peu de place."
		},
		{
			"event_id": "dialogic_023",
			"hide_dialogbox": true,
			"wait_seconds": 2
		},
		{
			"call_node": {
				"arguments": [
					"enter_subway"
				],
				"method_name": "dialogue_event",
				"target_node_path": "/root/Intro"
			},
			"event_id": "dialogic_042"
		},
		{
			"audio_bus": "Master",
			"background-music": "play",
			"event_id": "dialogic_031",
			"event_name": "BackgroundMusic",
			"fade_length": 1,
			"file": "",
			"volume": 0
		},
		{
			"call_node": {
				"arguments": [
					"animation"
				],
				"method_name": "dialogue_event",
				"target_node_path": "/root/Intro"
			},
			"event_id": "dialogic_042"
		},
		{
			"event_id": "dialogic_023",
			"hide_dialogbox": true,
			"wait_seconds": 5
		},
		{
			"character": "character-1677363460.json",
			"event_id": "dialogic_001",
			"portrait": "",
			"text": "C'était quoi ce bruit ???"
		},
		{
			"character": "character-1677363460.json",
			"event_id": "dialogic_001",
			"portrait": "",
			"text": "Pourquoi y a pu de lumière ?"
		},
		{
			"animation": "[Default]",
			"animation_length": 0,
			"change_mirror_portrait": false,
			"change_z_index": false,
			"character": "character-1681731225.json",
			"event_id": "dialogic_002",
			"mirror_portrait": false,
			"portrait": "Default",
			"portrait_definition": "",
			"position": {
				"0": false,
				"1": false,
				"2": true,
				"3": false,
				"4": false
			},
			"type": 0,
			"z_index": 0
		},
		{
			"character": "character-1677363460.json",
			"event_id": "dialogic_001",
			"portrait": "",
			"text": "Excusez-moi, vous avez entendu la même chose que moi ?"
		},
		{
			"character": "character-1681731225.json",
			"event_id": "dialogic_001",
			"portrait": "",
			"text": "..."
		},
		{
			"character": "character-1677363460.json",
			"event_id": "dialogic_001",
			"portrait": "",
			"text": "il n'a pas l'air de m'entendre..."
		},
		{
			"animation": "[Default]",
			"animation_length": 0,
			"change_mirror_portrait": false,
			"change_z_index": false,
			"character": "character-1681731225.json",
			"event_id": "dialogic_002",
			"mirror_portrait": false,
			"portrait": "",
			"portrait_definition": "",
			"position": {
				"0": false,
				"1": false,
				"2": false,
				"3": false,
				"4": false
			},
			"type": 1,
			"z_index": 0
		},
		{
			"event_id": "dialogic_023",
			"hide_dialogbox": true,
			"wait_seconds": 2
		},
		{
			"character": "character-1677363460.json",
			"event_id": "dialogic_001",
			"portrait": "",
			"text": "Et le métro vient de rédemarrer ?"
		},
		{
			"character": "character-1677363460.json",
			"event_id": "dialogic_001",
			"portrait": "",
			"text": "Je comprends vraiment rien.. Mais bon si je peut arriver à l'heure en cours, ça serait bien!"
		},
		{
			"call_node": {
				"arguments": [
					"end"
				],
				"method_name": "dialogue_event",
				"target_node_path": "/root/Intro"
			},
			"event_id": "dialogic_042"
		}
	],
	"metadata": {
		"dialogic-version": "1.4.5",
		"file": "timeline-1681730602.json",
		"name": "intro"
	}
}
